README.txt
carton.py
setup.py
carton.egg-info/PKG-INFO
carton.egg-info/SOURCES.txt
carton.egg-info/dependency_links.txt
carton.egg-info/entry_points.txt
carton.egg-info/not-zip-safe
carton.egg-info/top_level.txt