Metadata-Version: 1.0
Name: carton
Version: 0.3
Summary: make self-extracting virtualenvs
Home-page: http://k0s.org/hg/carton
Author: Jeff Hammel
Author-email: k0scist@gmail.com
License: MPL
Keywords: packaging
Platform: UNKNOWN
